lazyscan.py
helpers/__init__.py
helpers/chrome_cache_helpers.py
helpers/unity_cache_helpers.py
helpers/unity_hub.py
tests/__init__.py
tests/test_end_to_end_unity_reports.py
tests/test_lazyscan.py
tests/test_selection_parser.py
tests/test_unity.py
tests/test_unity_cache_helpers.py
tests/test_unity_hub.py
lazyscan-0.4.2.dist-info/LICENSE
lazyscan-0.4.2.dist-info/METADATA
lazyscan-0.4.2.dist-info/WHEEL
lazyscan-0.4.2.dist-info/entry_points.txt
lazyscan-0.4.2.dist-info/top_level.txt
lazyscan-0.4.2.dist-info/RECORD
