Metadata-Version: 2.2
Name: lazyscan
Version: 0.4.2
Summary: A lazy way to find what's eating your disk space - by TheLazyIndianTechie
Home-page: https://github.com/TheLazyIndianTechie/lazyscan
Author: TheLazyIndianTechie
Author-email: 
Project-URL: Bug Tracker, https://github.com/TheLazyIndianTechie/lazyscan/issues
Project-URL: Source Code, https://github.com/TheLazyIndianTechie/lazyscan
Keywords: disk space scanner cleaner cache macos terminal cli
Classifier: Programming Language :: Python :: 3
Classifier: Programming Language :: Python :: 3.6
Classifier: Programming Language :: Python :: 3.7
Classifier: Programming Language :: Python :: 3.8
Classifier: Programming Language :: Python :: 3.9
Classifier: Programming Language :: Python :: 3.10
Classifier: Programming Language :: Python :: 3.11
Classifier: Programming Language :: Python :: 3.12
Classifier: License :: OSI Approved :: MIT License
Classifier: Operating System :: OS Independent
Classifier: Environment :: Console
Classifier: Intended Audience :: Developers
Classifier: Intended Audience :: System Administrators
Classifier: Topic :: System :: Systems Administration
Classifier: Topic :: Utilities
Requires-Python: >=3.6
License-File: LICENSE
Dynamic: author
Dynamic: classifier
Dynamic: description
Dynamic: description-content-type
Dynamic: home-page
Dynamic: keywords
Dynamic: project-url
Dynamic: requires-python
Dynamic: summary
